alg/__init__.py
alg/query.py
alg/recursion.py
alg/sort.py
alg/spiderUseful/__init__.py
alg/spiderUseful/pcc.py
alg/spiderUseful/pccDetail.py
data_structure/__init__.py
data_structure/hashTable.py
data_structure/heap.py
data_structure/queue.py
data_structure/singleLinkList.py
data_structure/singleLinkListDemo.py
data_structure/skipList.py
data_structure/stack.py
pycode/__init__.py
pycode/createPyc.py
pycode/test.py
fandsimple_package-0.0.5.dist-info/METADATA
fandsimple_package-0.0.5.dist-info/WHEEL
fandsimple_package-0.0.5.dist-info/top_level.txt
fandsimple_package-0.0.5.dist-info/RECORD
